Metadata-Version: 2.1
Name: mclipp
Version: 1.1
Summary: Creating files with custom file size
Home-page: UNKNOWN
Author-email: portalproct@gmail.com
License: UNKNOWN
Platform: UNKNOWN
